{
  "auth": {
    "user_pool_id": "ap-south-1_NeXBd7R72",
    "aws_region": "ap-south-1",
    "user_pool_client_id": "6psmjsa5bhrv4490rdd0s0n1re",
    "identity_pool_id": "ap-south-1:00d89dc1-102f-475c-b9ce-355a0496295e",
    "mfa_methods": [],
    "standard_required_attributes": [
      "email"
    ],
    "username_attributes": [
      "email"
    ],
    "user_verification_types": [
      "email"
    ],
    "groups": [],
    "mfa_configuration": "NONE",
    "password_policy": {
      "min_length": 8,
      "require_lowercase": true,
      "require_numbers": true,
      "require_symbols": true,
      "require_uppercase": true
    },
    "unauthenticated_identities_enabled": true
  },
  "version": "1.4",
  "custom": {
    "apiEndpoint": "https://y3u1vnxxki.execute-api.ap-south-1.amazonaws.com/prod/"
  }
}